odoo8_addon_account_move_line_report_xls-8.0.0.6.0-py2.7-nspkg.pth
odoo8_addon_account_move_line_report_xls-8.0.0.6.0.dist-info/top_level.txt
odoo8_addon_account_move_line_report_xls-8.0.0.6.0.dist-info/WHEEL
odoo8_addon_account_move_line_report_xls-8.0.0.6.0.dist-info/RECORD
odoo8_addon_account_move_line_report_xls-8.0.0.6.0.dist-info/metadata.json
odoo8_addon_account_move_line_report_xls-8.0.0.6.0.dist-info/DESCRIPTION.rst
odoo8_addon_account_move_line_report_xls-8.0.0.6.0.dist-info/METADATA
odoo8_addon_account_move_line_report_xls-8.0.0.6.0.dist-info/namespace_packages.txt
odoo_addons/account_move_line_report_xls/account_move_line.py
odoo_addons/account_move_line_report_xls/__openerp__.py
odoo_addons/account_move_line_report_xls/__init__.py
odoo_addons/account_move_line_report_xls/README.rst
odoo_addons/account_move_line_report_xls/report/move_line_list_xls.py
odoo_addons/account_move_line_report_xls/report/__init__.py
odoo_addons/account_move_line_report_xls/report/move_line_list_xls.xml
odoo_addons/account_move_line_report_xls/i18n/nl.po
odoo_addons/account_move_line_report_xls/i18n/fr.po
odoo_addons/account_move_line_report_xls/static/description/journal_items.png
odoo_addons/account_move_line_report_xls/static/description/icon.svg
odoo_addons/account_move_line_report_xls/static/description/oca_logo.png
odoo_addons/account_move_line_report_xls/static/description/index.html
odoo_addons/account_move_line_report_xls/static/description/icon.png
